pyqbclient/__init__.py
pyqbclient/pyqbclient.py
pyqbclient-1.2.0.dist-info/LICENSE.txt
pyqbclient-1.2.0.dist-info/METADATA
pyqbclient-1.2.0.dist-info/WHEEL
pyqbclient-1.2.0.dist-info/top_level.txt
pyqbclient-1.2.0.dist-info/RECORD
