Metadata-Version: 2.1
Name: pyqbclient
Version: 1.2.0
Summary: Quickbase API client module
Author: Jeff MacDonald
Author-email: jeffmacd@protonmail.com
Classifier: Programming Language :: Python :: 3
Classifier: License :: OSI Approved :: MIT License
Classifier: Operating System :: OS Independent
Requires-Python: >=3.8
License-File: LICENSE.txt
Requires-Dist: numpy (>=1.21.4)
Requires-Dist: pandas (>=1.3.4)
Requires-Dist: requests (>=2.26.0)
Requires-Dist: lxml (>=4.6.4)
